{"container_type": "Author", "filled": ["basics", "publications", "indices", "counts"], "scholar_id": "BJUlpoMAAAAJ", "source": "AUTHOR_PROFILE_PAGE", "name": "Jiaqi Ma", "url_picture": "https://scholar.googleusercontent.com/citations?view_op=view_photo&user=BJUlpoMAAAAJ&citpid=7", "affiliation": "MBZUAI", "interests": ["Image Restoration", "Remote Sensing", "Image Signal Processor", "Computer Vision"], "email_domain": "@mbzuai.ac.ae", "homepage": "https://leonmakise.github.io/", "citedby": 591, "publications": {"BJUlpoMAAAAJ:UeHWp8X0CEIC": {"container_type": "Publication", "source": "AUTHOR_PUBLICATION_ENTRY", "bib": {"title": "HyperSIGMA: Hyperspectral intelligence comprehension foundation model", "pub_year": "2025"}, "filled": false, "author_pub_id": "BJUlpoMAAAAJ:UeHWp8X0CEIC", "num_citations": 206, "citedby_url": "https://scholar.google.com/scholar?oi=bibs&hl=en&cites=5070225043786886624", "cites_id": ["5070225043786886624"]}, "BJUlpoMAAAAJ:qjMakFHDy7sC": {"container_type": "Publication", "source": "AUTHOR_PUBLICATION_ENTRY", "bib": {"title": "Prores: Exploring degradation-aware visual prompt for universal image restoration", "pub_year": "2023"}, "filled": false, "author_pub_id": "BJUlpoMAAAAJ:qjMakFHDy7sC", "num_citations": 113, "citedby_url": "https://scholar.google.com/scholar?oi=bibs&hl=en&cites=255724861176068868", "cites_id": ["255724861176068868"]}, "BJUlpoMAAAAJ:u-x6o8ySG0sC": {"container_type": "Publication", "source": "AUTHOR_PUBLICATION_ENTRY", "bib": {"title": "Discriminative subspace matrix factorization for multiview data clustering", "pub_year": "2021"}, "filled": false, "author_pub_id": "BJUlpoMAAAAJ:u-x6o8ySG0sC", "num_citations": 93, "citedby_url": "https://scholar.google.com/scholar?oi=bibs&hl=en&cites=4218977518517963622", "cites_id": ["4218977518517963622"]}, "BJUlpoMAAAAJ:_FxGoFyzp5QC": {"container_type": "Publication", "source": "AUTHOR_PUBLICATION_ENTRY", "bib": {"title": "Perceive-ir: Learning to perceive degradation better for all-in-one image restoration", "pub_year": "2025"}, "filled": false, "author_pub_id": "BJUlpoMAAAAJ:_FxGoFyzp5QC", "num_citations": 80, "citedby_url": "https://scholar.google.com/scholar?oi=bibs&hl=en&cites=7094997423554835673", "cites_id": ["7094997423554835673"]}, "BJUlpoMAAAAJ:2osOgNQ5qMEC": {"container_type": "Publication", "source": "AUTHOR_PUBLICATION_ENTRY", "bib": {"title": "Restoration and enhancement on low exposure raw images by joint demosaicing and denoising", "pub_year": "2023"}, "filled": false, "author_pub_id": "BJUlpoMAAAAJ:2osOgNQ5qMEC", "num_citations": 28, "citedby_url": "https://scholar.google.com/scholar?oi=bibs&hl=en&cites=12712216209392226717", "cites_id": ["12712216209392226717"]}, "BJUlpoMAAAAJ:kNdYIx-mwKoC": {"container_type": "Publication", "source": "AUTHOR_PUBLICATION_ENTRY", "bib": {"title": "The eleventh NTIRE 2026 efficient super-resolution challenge report", "pub_year": "2026"}, "filled": false, "author_pub_id": "BJUlpoMAAAAJ:kNdYIx-mwKoC", "num_citations": 21, "citedby_url": "https://scholar.google.com/scholar?oi=bibs&hl=en&cites=9004608651540750033", "cites_id": ["9004608651540750033"]}, "BJUlpoMAAAAJ:9yKSN-GCB0IC": {"container_type": "Publication", "source": "AUTHOR_PUBLICATION_ENTRY", "bib": {"title": "Elmformer: Efficient raw image restoration with a locally multiplicative transformer", "pub_year": "2022"}, "filled": false, "author_pub_id": "BJUlpoMAAAAJ:9yKSN-GCB0IC", "num_citations": 12, "citedby_url": "https://scholar.google.com/scholar?oi=bibs&hl=en&cites=2461080983823425890", "cites_id": ["2461080983823425890"]}, "BJUlpoMAAAAJ:d1gkVwhDpl0C": {"container_type": "Publication", "source": "AUTHOR_PUBLICATION_ENTRY", "bib": {"title": "Pseudo facial generation with extreme poses for face recognition", "pub_year": "2021"}, "filled": false, "author_pub_id": "BJUlpoMAAAAJ:d1gkVwhDpl0C", "num_citations": 10, "citedby_url": "https://scholar.google.com/scholar?oi=bibs&hl=en&cites=8264673335847200273", "cites_id": ["8264673335847200273"]}, "BJUlpoMAAAAJ:u5HHmVD_uO8C": {"container_type": "Publication", "source": "AUTHOR_PUBLICATION_ENTRY", "bib": {"title": "Pseudo Supervised Matrix Factorization in Discriminative Subspace.", "pub_year": "2019"}, "filled": false, "author_pub_id": "BJUlpoMAAAAJ:u5HHmVD_uO8C", "num_citations": 9, "citedby_url": "https://scholar.google.com/scholar?oi=bibs&hl=en&cites=998777618330291331", "cites_id": ["998777618330291331"]}, "BJUlpoMAAAAJ:MXK_kJrjxJIC": {"container_type": "Publication", "source": "AUTHOR_PUBLICATION_ENTRY", "bib": {"title": "Simtoken: A simple baseline for referring audio-visual segmentation", "pub_year": "2026"}, "filled": false, "author_pub_id": "BJUlpoMAAAAJ:MXK_kJrjxJIC", "num_citations": 7, "citedby_url": "https://scholar.google.com/scholar?oi=bibs&hl=en&cites=9475084539554913964", "cites_id": ["9475084539554913964"]}, "BJUlpoMAAAAJ:0EnyYjriUFMC": {"container_type": "Publication", "source": "AUTHOR_PUBLICATION_ENTRY", "bib": {"title": "Token Expand-Merge: Training-Free Token Compression for Vision-Language-Action Models", "pub_year": "2025"}, "filled": false, "author_pub_id": "BJUlpoMAAAAJ:0EnyYjriUFMC", "num_citations": 3, "citedby_url": "https://scholar.google.com/scholar?oi=bibs&hl=en&cites=2730177176327379441", "cites_id": ["2730177176327379441"]}, "BJUlpoMAAAAJ:KlAtU1dfN6UC": {"container_type": "Publication", "source": "AUTHOR_PUBLICATION_ENTRY", "bib": {"title": "LoViF 2026 challenge on real-world all-in-one image restoration: Methods and results", "pub_year": "2026"}, "filled": false, "author_pub_id": "BJUlpoMAAAAJ:KlAtU1dfN6UC", "num_citations": 2, "citedby_url": "https://scholar.google.com/scholar?oi=bibs&hl=en&cites=2869677531973864191", "cites_id": ["2869677531973864191"]}, "BJUlpoMAAAAJ:roLk4NBRz8UC": {"container_type": "Publication", "source": "AUTHOR_PUBLICATION_ENTRY", "bib": {"title": "Hierarchical graph attention network for no-reference omnidirectional image quality assessment", "pub_year": "2025"}, "filled": false, "author_pub_id": "BJUlpoMAAAAJ:roLk4NBRz8UC", "num_citations": 2, "citedby_url": "https://scholar.google.com/scholar?oi=bibs&hl=en&cites=10161326504576585384", "cites_id": ["10161326504576585384"]}, "BJUlpoMAAAAJ:LkGwnXOMwfcC": {"container_type": "Publication", "source": "AUTHOR_PUBLICATION_ENTRY", "bib": {"title": "HDL: Hybrid and Dynamic Learning for Fake Face Recognition", "pub_year": "2025"}, "filled": false, "author_pub_id": "BJUlpoMAAAAJ:LkGwnXOMwfcC", "num_citations": 2, "citedby_url": "https://scholar.google.com/scholar?oi=bibs&hl=en&cites=12539262096735351186", "cites_id": ["12539262096735351186"]}, "BJUlpoMAAAAJ:3fE2CSJIrl8C": {"container_type": "Publication", "source": "AUTHOR_PUBLICATION_ENTRY", "bib": {"title": "Audit After Segmentation: Reference-Free Mask Quality Assessment for Language-Referred Audio-Visual Segmentation", "pub_year": "2026"}, "filled": false, "author_pub_id": "BJUlpoMAAAAJ:3fE2CSJIrl8C", "num_citations": 1, "citedby_url": "https://scholar.google.com/scholar?oi=bibs&hl=en&cites=4170363944336413608", "cites_id": ["4170363944336413608"]}, "BJUlpoMAAAAJ:5nxA0vEk-isC": {"container_type": "Publication", "source": "AUTHOR_PUBLICATION_ENTRY", "bib": {"title": "ClusIR: Towards Cluster-Guided All-in-One Image Restoration", "pub_year": "2025"}, "filled": false, "author_pub_id": "BJUlpoMAAAAJ:5nxA0vEk-isC", "num_citations": 1, "citedby_url": "https://scholar.google.com/scholar?oi=bibs&hl=en&cites=10989942125644397249", "cites_id": ["10989942125644397249"]}, "BJUlpoMAAAAJ:8k81kl-MbHgC": {"container_type": "Publication", "source": "AUTHOR_PUBLICATION_ENTRY", "bib": {"title": "EvoIR: Towards All-in-One Image Restoration via Evolutionary Frequency Modulation", "pub_year": "2025"}, "filled": false, "author_pub_id": "BJUlpoMAAAAJ:8k81kl-MbHgC", "num_citations": 1, "citedby_url": "https://scholar.google.com/scholar?oi=bibs&hl=en&cites=13239407045139053848", "cites_id": ["13239407045139053848"]}, "BJUlpoMAAAAJ:Se3iqnhoufwC": {"container_type": "Publication", "source": "AUTHOR_PUBLICATION_ENTRY", "bib": {"title": "RainDiff: End-to-end Precipitation Nowcasting Via Token-wise Attention Diffusion", "pub_year": "2025"}, "filled": false, "author_pub_id": "BJUlpoMAAAAJ:Se3iqnhoufwC", "num_citations": 0}}, "citedby5y": 589, "hindex": 9, "hindex5y": 9, "i10index": 8, "i10index5y": 8, "cites_per_year": {"2020": 2, "2021": 15, "2022": 31, "2023": 30, "2024": 76, "2025": 240, "2026": 195}, "updated": "2026-05-10 09:44:51.579014"}